nudb/__init__.py
nudb/customErrorMessage.py
nudb/error.py
nudb/nudb.py
nudb/tools.py
nudb-1.1.4.dist-info/METADATA
nudb-1.1.4.dist-info/WHEEL
nudb-1.1.4.dist-info/top_level.txt
nudb-1.1.4.dist-info/RECORD
