Metadata-Version: 2.1
Name: nudb
Version: 1.1.4
Summary: For nudb
Home-page: https://github.com/wshs0713/nudb
Author: Szu-Hsuan, Wu
Author-email: shuan@csie.io
License: docs/LICENSE.txt
Keywords: nudb
Platform: UNKNOWN
Requires-Dist: requests (>=2.18.0)
